setup.cfg
setup.py
j2pbs/__init__.py
j2pbs/__main__.py
j2pbs/__version__.py
j2pbs/exceptions.py
j2pbs/json_utils.py
j2pbs/model.py
j2pbs/pbs_utils.py
j2pbs/semantic.py
j2pbs.egg-info/PKG-INFO
j2pbs.egg-info/SOURCES.txt
j2pbs.egg-info/dependency_links.txt
j2pbs.egg-info/top_level.txt