Metadata-Version: 1.1
Name: j2pbs
Version: 0.1.2
Summary: Submit PBS jobs with json file format.
Home-page: https://github.com/Nanguage/j2pbs
Author: Nanguage
Author-email: nanguage@yahoo.com
License: Apache 2.0
Keywords: json pbs
Platform: UNKNOWN
Classifier: Natural Language :: English
Classifier: License :: OSI Approved :: Apache Software License
Classifier: Programming Language :: Python
Classifier: Programming Language :: Python :: 2.6
Classifier: Programming Language :: Python :: 2.7
Classifier: Programming Language :: Python :: 3.4
Classifier: Programming Language :: Python :: 3.5
Classifier: Programming Language :: Python :: 3.6
Classifier: Programming Language :: Python :: Implementation :: CPython
